dressy/__init__.py
dressy-0.0.1.dist-info/WHEEL
dressy-0.0.1.dist-info/METADATA
dressy-0.0.1.dist-info/RECORD
