Metadata-Version: 2.1
Name: dressy
Version: 0.0.1
Summary: Fast python linter.
Author: zhivykh
Author-email: zivih.n@gmail.com
Requires-Python: >=3.10,<4.0
Classifier: Programming Language :: Python :: 3
Classifier: Programming Language :: Python :: 3.10
Classifier: Programming Language :: Python :: 3.11
Requires-Dist: twine (>=4.0.1,<5.0.0)
